spprval/__init__.py
spprval/database/Adapter.py
spprval/database/DBWrapper.py
spprval/database/DataSource.py
spprval/database/__init__.py
spprval/dataset/BaseDataset.py
spprval/dataset/KSGDataset.py
spprval/dataset/ObjectNameProcessor.py
spprval/dataset/PlanDataset.py
spprval/dataset/ValidationDataset.py
spprval/validation/SPPRVal.py
spprval/validation/__init__.py
spprval/validation/aggregator.py
spprval/validation/expert_metrics_estimator.py
spprval/validation/rendering.py
spprval/validation/stats_calculator.py
spprval/validation/tables/brave_work_res.csv
spprval/validation/tables/journal_mapped.json
spprval/validation/tables/links_history_messoyaha_new.csv
spprval/validation/tables/links_history_messoyaha_with_granular_smr_v4.csv
spprval/validation/tables/precalculated_brave_coefficients.csv
spprval/validation/validators/BaseValidator.py
spprval/validation/validators/JournalValidation.py
spprval/validation/validators/ResourcesValidator.py
spprval/validation/validators/TimeValidator.py
spprval/validation/validators/WorksValidator.py
spprval/validation/validators/__init__.py
spprval-0.3.6.dist-info/METADATA
spprval-0.3.6.dist-info/WHEEL
spprval-0.3.6.dist-info/RECORD
