Metadata-Version: 2.1
Name: SPPRVAL
Version: 0.3.6
Summary: 
Author: Roman223
Author-email: romius2001@gmail.com
Requires-Python: >=3.10,<4.0
Classifier: Programming Language :: Python :: 3
Classifier: Programming Language :: Python :: 3.10
Classifier: Programming Language :: Python :: 3.11
Classifier: Programming Language :: Python :: 3.12
Requires-Dist: idbadapter (>=2.1.0,<2.2.0)
Requires-Dist: matplotlib (>=3.6.2)
Requires-Dist: numpy (>=1.25.0)
Requires-Dist: numpy-indexed (==0.3.5)
Requires-Dist: pandas (>=2.0.0)
Requires-Dist: reportlab
Requires-Dist: rich (>=13.5.3)
Requires-Dist: scipy (>=1.8.0)
Requires-Dist: seaborn (>=0.11.2)
